{
  "metro_key": "dallas",
  "kind": "acs_commute_2019",
  "metro_config": {
    "cbsa_code": "19100",
    "counties": [
      [
        "48",
        "113"
      ],
      [
        "48",
        "121"
      ],
      [
        "48",
        "257"
      ],
      [
        "48",
        "439"
      ]
    ],
    "zip_prefixes": [
      "75",
      "76"
    ],
    "utm_zone": 32614,
    "cbd_points": [
      [
        32.7767,
        -96.797
      ],
      [
        32.7555,
        -97.3308
      ]
    ]
  },
  "provenance": "pipeline-build",
  "git_commit": "f2cf29ededfe64abc6418f73f97071c61d17e93f",
  "regenerated_at_commit": null,
  "run_timestamp_utc": "2026-07-18T01:45:30.870460+00:00",
  "cbsa_vintage": "ACS 2024",
  "source_urls": {
    "acs": "https://api.census.gov/data/2019/acs/acs5",
    "tiger": "https://tigerweb.geo.census.gov/arcgis/rest/services (CBSA/ZCTA/tract)"
  },
  "output_csv": "acs_commute_2019_dallas.csv",
  "row_count": 186,
  "columns": [
    {
      "name": "ZCTA5CE",
      "dtype": "Int64"
    },
    {
      "name": "commute_min_proxy_2019",
      "dtype": "Float64"
    },
    {
      "name": "ttw_total_2019",
      "dtype": "Int64"
    }
  ],
  "sha256": "875dabeb4b2373aa3e913f9553fdfddd25a162e9cf7469eb645059c911ea117e"
}